interval_search/__init__.py
interval_search/binary_search.py
interval_search/binary_search_iterative.py
interval_search/binary_search_recursive.py
interval_search/curried_binary_search.py
interval_search/curried_binary_search_iterative.py
interval_search/curried_binary_search_recursive.py
interval_search/curried_doubling_search.py
interval_search/doubling_search.py
interval_search/interval_search.py
interval_search-0.5.2.dist-info/AUTHORS.rst
interval_search-0.5.2.dist-info/LICENSE
interval_search-0.5.2.dist-info/METADATA
interval_search-0.5.2.dist-info/WHEEL
interval_search-0.5.2.dist-info/top_level.txt
interval_search-0.5.2.dist-info/RECORD
