Metadata-Version: 2.1
Name: interval-search
Version: 0.5.2
Summary: interval-search provides predicate-based binary and doubling search implementations
Home-page: https://github.com/mmore500/interval-search
Author: Matthew Andres Moreno
Author-email: m.more500@gmail.com
License: MIT license
Keywords: interval-search
Platform: UNKNOWN
Classifier: Development Status :: 2 - Pre-Alpha
Classifier: Intended Audience :: Developers
Classifier: License :: OSI Approved :: MIT License
Classifier: Natural Language :: English
Classifier: Programming Language :: Python :: 3
Classifier: Programming Language :: Python :: 3.7
Classifier: Programming Language :: Python :: 3.8
Classifier: Programming Language :: Python :: 3.9
Classifier: Programming Language :: Python :: 3.10
Classifier: Programming Language :: Python :: 3.11
Requires-Python: >=3.6
